{
	"name": "DataCopy",
	"properties": {
		"activities": [
			{
				"name": "Ingest to Src",
				"type": "Copy",
				"dependsOn": [],
				"policy": {
					"timeout": "0.12:00:00",
					"retry": 0,
					"retryIntervalInSeconds": 30,
					"secureOutput": false,
					"secureInput": false
				},
				"userProperties": [],
				"typeProperties": {
					"source": {
						"type": "BinarySource",
						"storeSettings": {
							"type": "AzureBlobFSReadSettings",
							"recursive": true,
							"deleteFilesAfterCompletion": false
						},
						"formatSettings": {
							"type": "BinaryReadSettings"
						}
					},
					"sink": {
						"type": "BinarySink",
						"storeSettings": {
							"type": "AzureBlobFSWriteSettings"
						}
					},
					"enableStaging": false
				},
				"inputs": [
					{
						"referenceName": "azc000dlsdpdev1_ingest",
						"type": "DatasetReference"
					}
				],
				"outputs": [
					{
						"referenceName": "azc000dlsdpdev2_src",
						"type": "DatasetReference"
					}
				]
			}
		],
		"folder": {
			"name": "pilot_zeal"
		},
		"annotations": [],
		"lastPublishTime": "2023-10-19T06:37:27Z"
	},
	"type": "Microsoft.DataFactory/factories/pipelines"
}